setup.cfg
setup.py
kqray/__init__.py
kqray/kqray.py
kqray.egg-info/PKG-INFO
kqray.egg-info/SOURCES.txt
kqray.egg-info/dependency_links.txt
kqray.egg-info/top_level.txt