Metadata-Version: 1.0
Name: kqray
Version: 0.0.1051
Summary: this module for raycasting
Home-page: UNKNOWN
Author: UNKNOWN
Author-email: kolyaleonof@yandex.ru
License: UNKNOWN
Platform: UNKNOWN
